CloudStackAIO/CloudStack.py
CloudStackAIO/__init__.py
tests/CloudStackAIO_t/__init__.py
tests/CloudStackAIO_t/test_CloudStack.py
CloudStackAIO-0.0.7.dist-info/LICENSE.txt
CloudStackAIO-0.0.7.dist-info/METADATA
CloudStackAIO-0.0.7.dist-info/WHEEL
CloudStackAIO-0.0.7.dist-info/top_level.txt
CloudStackAIO-0.0.7.dist-info/RECORD
