Metadata-Version: 2.1
Name: CloudStackAIO
Version: 0.0.7
Summary: Very thin Python CloudStack client using asyncio
Home-page: https://github.com/giffels/CloudStackAIO
Author: Manuel Giffels
Author-email: giffels@gmail.com
License: UNKNOWN
Project-URL: Bug Reports, https://github.com/giffels/CloudStackAIO/issues
Project-URL: Source, https://github.com/giffels/CloudStackAIO
Keywords: asyncio cloudstack client
Platform: UNKNOWN
Classifier: Development Status :: 3 - Alpha
Classifier: Intended Audience :: Developers
Classifier: Intended Audience :: System Administrators
Classifier: Intended Audience :: Information Technology
Classifier: Intended Audience :: Science/Research
Classifier: Operating System :: OS Independent
Classifier: Topic :: Internet :: WWW/HTTP :: Session
Classifier: Framework :: AsyncIO
Classifier: License :: OSI Approved :: MIT License
Classifier: Programming Language :: Python :: 3.6
Requires-Dist: aiohttp
